electronica/Laba3/code/src/Lab_3.v
//iverilog -o ./compiled ./src/Lab_3.v ./src/indicator_tb.v
//vvp ./compiled

module led_controller (
    input wire clk,
    input wire [1:0] buttons,      // Две кнопки
    input wire [5:0] switches,     // Шесть переключателей
    output reg [5:0] leds          // Шесть светодиодов
);

    reg invert;  // Переменная для хранения состояния инверсии
    integer i;

    // Управление светодиодами
    always @(posedge clk) begin
        if (buttons[0] | buttons[1]) begin
            invert <= ~invert;  // Инвертируем состояние при нажатии любой кнопки
        end
    end

    // Обновление состояния светодиодов с учетом переключателей и инверсии
    always @* begin
        for (i = 0; i < 6; i = i + 1) begin
            if (invert)
                leds[i] = ~switches[i];
            else
                leds[i] = switches[i];
        end
    end

endmodule

electronica/Laba3/code/src/indicator_tb.v
`timescale 1ns / 1ns

module led_controller_tb();

    reg clk;
    reg [5:0] switches;  // Вход для переключателей
    reg [1:0] buttons;   // Вход для кнопок
    wire [5:0] leds;     // Выход для светодиодов

    // Подключение тестируемого модуля
    led_controller uut (
        .clk(clk),
        .switches(switches),
        .buttons(buttons),
        .leds(leds)
    );

    // Генерация тактового сигнала с периодом 10 нс (частота 100 МГц)
    initial begin
        clk = 0;
        forever #(5) clk = ~clk;
    end

    // Начальные значения для переключателей и кнопок
    initial begin
        switches = 6'b000000; // Все переключатели выключены
        buttons = 6'b000000;  // Все кнопки не нажаты
        
        // Тестовые сценарии
        // Включение всех светодиодов по очереди
        #10 switches[0] = 1;  // Включаем 1-й светодиод
        #10 switches[0] = 0;  // Выключаем

        #10 switches[1] = 1;  // Включаем 2-й светодиод
        #10 switches[1] = 0;  // Выключаем

        #10 switches[2] = 1;  // Включаем 3-й светодиод
        #10 switches[2] = 0;  // Выключаем

        #10 switches[3] = 1;  // Включаем 4-й светодиод
        #10 switches[3] = 0;  // Выключаем

        #10 switches[4] = 1;  // Включаем 5-й светодиод
        #10 switches[4] = 0;  // Выключаем

        #10 switches[5] = 1;  // Включаем 6-й светодиод
        #10 switches[5] = 0;  // Выключаем

        // Инверсия состояния всех светодиодов по очереди
        #10 switches[0] = 1; buttons[0] = 1; // Включаем 1-й и инвертируем
        #10 buttons[0] = 0; // Отпускаем кнопку

        #10 switches[1] = 1; buttons[1] = 1; // Включаем 2-й и инвертируем
        #10 buttons[1] = 0; // Отпускаем кнопку

        #10 switches[2] = 1; buttons[2] = 1; // Включаем 3-й и инвертируем
        #10 buttons[2] = 0; // Отпускаем кнопку

        #10 switches[3] = 1; buttons[3] = 1; // Включаем 4-й и инвертируем
        #10 buttons[3] = 0; // Отпускаем кнопку

        #10 switches[4] = 1; buttons[4] = 1; // Включаем 5-й и инвертируем
        #10 buttons[4] = 0; // Отпускаем кнопку

        #10 switches[5] = 1; buttons[5] = 1; // Включаем 6-й и инвертируем
        #10 buttons[5] = 0; // Отпускаем кнопку
        
        // Завершение симуляции через 200 нс
        #200 $finish;
    end

    // Сохранение результата симуляции в файл VCD
    initial begin
        $dumpfile("led_controller_tb_out.vcd");
        $dumpvars(0, led_controller_tb);
    end

endmodule

electronica/Laba3/code/led_controller_tb_out.vcd
$date
	Wed Oct 30 00:52:19 2024
$end
$version
	Icarus Verilog
$end
$timescale
	1ns
$end
$scope module led_controller_tb $end
$var wire 6 ! leds [5:0] $end
$var reg 2 " buttons [1:0] $end
$var reg 1 # clk $end
$var reg 6 $ switches [5:0] $end
$scope module uut $end
$var wire 2 % buttons [1:0] $end
$var wire 1 # clk $end
$var wire 6 & switches [5:0] $end
$var reg 1 ' invert $end
$var reg 6 ( leds [5:0] $end
$var integer 32 ) i [31:0] $end
$upscope $end
$upscope $end
$enddefinitions $end
$comment Show the parameter values. $end
$dumpall
$end
#0
$dumpvars
b110 )
b0 (
x'
b0 &
b0 %
b0 $
0#
b0 "
b0 !
$end
#5
1#
#10
b1 !
b1 (
b110 )
0#
b1 $
b1 &
#15
1#
#20
b0 !
b0 (
b110 )
0#
b0 $
b0 &
#25
1#
#30
b10 !
b10 (
b110 )
0#
b10 $
b10 &
#35
1#
#40
b0 !
b0 (
b110 )
0#
b0 $
b0 &
#45
1#
#50
b100 !
b100 (
b110 )
0#
b100 $
b100 &
#55
1#
#60
b0 !
b0 (
b110 )
0#
b0 $
b0 &
#65
1#
#70
b1000 !
b1000 (
b110 )
0#
b1000 $
b1000 &
#75
1#
#80
b0 !
b0 (
b110 )
0#
b0 $
b0 &
#85
1#
#90
b10000 !
b10000 (
b110 )
0#
b10000 $
b10000 &
#95
1#
#100
b0 !
b0 (
b110 )
0#
b0 $
b0 &
#105
1#
#110
b100000 !
b100000 (
b110 )
0#
b100000 $
b100000 &
#115
1#
#120
b0 !
b0 (
b110 )
0#
b0 $
b0 &
#125
1#
#130
b1 !
b1 (
b110 )
0#
b1 "
b1 %
b1 $
b1 &
#135
1#
#140
0#
b0 "
b0 %
#145
1#
#150
b11 !
b11 (
b110 )
0#
b10 "
b10 %
b11 $
b11 &
#155
1#
#160
0#
b0 "
b0 %
#165
1#
#170
b111 !
b111 (
b110 )
0#
b111 $
b111 &
#175
1#
#180
0#
#185
1#
#190
b1111 !
b1111 (
b110 )
0#
b1111 $
b1111 &
#195
1#
#200
0#
#205
1#
#210
b11111 !
b11111 (
b110 )
0#
b11111 $
b11111 &
#215
1#
#220
0#
#225
1#
#230
b111111 !
b111111 (
b110 )
0#
b111111 $
b111111 &
