electronica/Laba2/code/pmw_led/src/pwm_led.v
module pwm_led
#(parameter  LED_COUNT = 6, parameter COOLDOWN = 21) // для симуляции COOLDOWN = 3, для запуска 21
(
    input clk,
    input  up,
    input down,
    output [LED_COUNT-1:0] led  
);


reg [2:0] shift;
reg [COOLDOWN-1:0] cooldown;
reg [2:0] counter;

always @(posedge clk)
begin
    if (counter < LED_COUNT-1)
        counter <= counter + 1'b1;
    else
        counter <= 0;
end

always @(posedge clk)
begin
    if (!cooldown)
    begin
        if (!up)
        begin
            cooldown <= 2**COOLDOWN-1;
            if (shift < LED_COUNT-1)
                shift <= shift + 1'b1;
            else
                shift <= 0;
    end
    else if (!down)
    begin
        cooldown <= 2**COOLDOWN-1;
        if (shift > 0)
            shift <= shift - 1'b1;
        else
            shift <= LED_COUNT-1;
        end
    end
    else
        cooldown <= cooldown - 1'b1;
end

genvar i;
generate
        for (i = 0; i < LED_COUNT; i = i + 1)
        begin : led_block  
            assign led[i] = counter > i % LED_COUNT;
        end
endgenerate

endmodule

electronica/Laba2/code/pmw_led/src/pwm_led_tb.v
`timescale 1ns / 1ns

module pwm_led_tb();

reg clk;  // Тактовый сигнал
reg up;
reg down;
wire [5:0] led;  // Светодиоды

// Экземпляр тестируемого модуля
pwm_led #(6, 21) uut(.clk(clk), .up(up), .down(down), .led(led));

// Генерация тактового сигнала с периодом 10 нс (частота 100 МГц)
initial begin
    clk = 0;
    forever #(5) clk = ~clk;  // Период 10 нс
end

initial
begin
    up <= 1;
    down <= 1;
    #20 up <= 0;
    #180 up <= 1;
    #200 down <= 0;
    #200 down <= 1;
end


// Завершение симуляции через 1000 нс
initial begin
    #1000 $finish;
end

// Сохранение результата симуляции в файл VCD для анализа
initial begin
    $dumpfile("pwm_led_out.vcd");
    $dumpvars(0, pwm_led_tb);
end

endmodule

electronica/Laba2/code/pmw_led/pwm_led_out.vcd
$date
	Fri Oct 04 13:03:09 2024
$end
$version
	Icarus Verilog
$end
$timescale
	1ns
$end
$scope module pwm_led_tb $end
$var wire 6 ! led [5:0] $end
$var reg 1 " clk $end
$var reg 1 # down $end
$var reg 1 $ up $end
$scope module uut $end
$var wire 1 " clk $end
$var wire 1 # down $end
$var wire 1 $ up $end
$var wire 6 % led [5:0] $end
$var parameter 32 & COOLDOWN $end
$var parameter 32 ' LED_COUNT $end
$var reg 21 ( cooldown [20:0] $end
$var reg 3 ) counter [2:0] $end
$var reg 3 * shift [2:0] $end
$scope begin led_block[0] $end
$var parameter 2 + i $end
$upscope $end
$scope begin led_block[1] $end
$var parameter 2 , i $end
$upscope $end
$scope begin led_block[2] $end
$var parameter 3 - i $end
$upscope $end
$scope begin led_block[3] $end
$var parameter 3 . i $end
$upscope $end
$scope begin led_block[4] $end
$var parameter 4 / i $end
$upscope $end
$scope begin led_block[5] $end
$var parameter 4 0 i $end
$upscope $end
$upscope $end
$upscope $end
$enddefinitions $end
$comment Show the parameter values. $end
$dumpall
b101 0
b100 /
b11 .
b10 -
b1 ,
b0 +
b110 '
b10101 &
$end
#0
$dumpvars
bx *
bx )
bx (
bx %
1$
1#
0"
bx !
$end
#5
b0 !
b0 %
b0 )
1"
#10
0"
#15
b1 !
b1 %
b1 )
1"
#20
0$
0"
#25
b11 !
b11 %
b10 )
1"
#30
0"
#35
b111 !
b111 %
b11 )
1"
#40
0"
#45
b1111 !
b1111 %
b100 )
1"
#50
0"
#55
b11111 !
b11111 %
b101 )
1"
#60
0"
#65
b0 !
b0 %
b0 )
1"
#70
0"
#75
b1 !
b1 %
b1 )
1"
#80
0"
#85
b11 !
b11 %
b10 )
1"
#90
0"
#95
b111 !
b111 %
b11 )
1"
#100
0"
#105
b1111 !
b1111 %
b100 )
1"
#110
0"
#115
b11111 !
b11111 %
b101 )
1"
#120
0"
#125
b0 !
b0 %
b0 )
1"
#130
0"
#135
b1 !
b1 %
b1 )
1"
#140
0"
#145
b11 !
b11 %
b10 )
1"
#150
0"
#155
b111 !
b111 %
b11 )
1"
#160
0"
#165
b1111 !
b1111 %
b100 )
1"
#170
0"
#175
b11111 !
b11111 %
b101 )
1"
#180
0"
#185
b0 !
b0 %
b0 )
1"
#190
0"
#195
b1 !
b1 %
b1 )
1"
#200
1$
0"
#205
b11 !
b11 %
b10 )
1"
#210
0"
#215
b111 !
b111 %
b11 )
1"
#220
0"
#225
b1111 !
b1111 %
b100 )
1"
#230
0"
#235
b11111 !
b11111 %
b101 )
1"
#240
0"
#245
b0 !
b0 %
b0 )
1"
#250
0"
#255
b1 !
b1 %
b1 )
1"
#260
0"
#265
b11 !
b11 %
b10 )
1"
#270
0"
#275
b111 !
b111 %
b11 )
1"
#280
0"
#285
b1111 !
b1111 %
b100 )
1"
#290
0"
#295
b11111 !
b11111 %
b101 )
1"
#300
0"
#305
b0 !
b0 %
b0 )
1"
#310
0"
#315
b1 !
b1 %
b1 )
1"
#320
0"
#325
b11 !
b11 %
b10 )
1"
#330
0"
#335
b111 !
b111 %
b11 )
1"
#340
0"
#345
b1111 !
b1111 %
b100 )
1"
#350
0"
#355
b11111 !
b11111 %
b101 )
1"
#360
0"
#365
b0 !
b0 %
b0 )
1"
#370
0"
#375
b1 !
b1 %
b1 )
1"
#380
0"
#385
b11 !
b11 %
b10 )
1"
#390
0"
#395
b111 !
b111 %
b11 )
1"
#400
0#
0"
#405
b1111 !
b1111 %
b100 )
1"
#410
0"
#415
b11111 !
b11111 %
b101 )
1"
#420
0"
#425
b0 !
b0 %
b0 )
1"
#430
0"
#435
b1 !
b1 %
b1 )
1"
#440
0"
#445
b11 !
b11 %
b10 )
1"
#450
0"
#455
b111 !
b111 %
b11 )
1"
#460
0"
#465
b1111 !
b1111 %
b100 )
1"
#470
0"
#475
b11111 !
b11111 %
b101 )
1"
#480
0"
#485
b0 !
b0 %
b0 )
1"
#490
0"
#495
b1 !
b1 %
b1 )
1"
#500
0"
#505
b11 !
b11 %
b10 )
1"
#510
0"
#515
b111 !
b111 %
b11 )
1"
#520
0"
#525
b1111 !
b1111 %
b100 )
1"
#530
0"
#535
b11111 !
b11111 %
b101 )
1"
#540
0"
#545
b0 !
b0 %
b0 )
1"
#550
0"
#555
b1 !
b1 %
b1 )
1"
#560
0"
#565
b11 !
b11 %
b10 )
1"
#570
0"
#575
b111 !
b111 %
b11 )
1"
#580
0"
#585
b1111 !
b1111 %
b100 )
1"
#590
0"
#595
b11111 !
b11111 %
b101 )
1"
#600
1#
0"
#605
b0 !
b0 %
b0 )
1"
#610
0"
#615
b1 !
b1 %
b1 )
1"
#620
0"
#625
b11 !
b11 %
b10 )
1"
#630
0"
#635
b111 !
b111 %
b11 )
1"
#640
0"
#645
b1111 !
b1111 %
b100 )
1"
#650
0"
#655
b11111 !
b11111 %
b101 )
1"
#660
0"
#665
b0 !
b0 %
b0 )
1"
#670
0"
#675
b1 !
b1 %
b1 )
1"
#680
0"
#685
b11 !
b11 %
b10 )
1"
#690
0"
#695
b111 !
b111 %
b11 )
1"
#700
0"
#705
b1111 !
b1111 %
b100 )
1"
#710
0"
#715
b11111 !
b11111 %
b101 )
1"
#720
0"
#725
b0 !
b0 %
b0 )
1"
#730
0"
#735
b1 !
b1 %
b1 )
1"
#740
0"
#745
b11 !
b11 %
b10 )
1"
#750
0"
#755
b111 !
b111 %
b11 )
1"
#760
0"
#765
b1111 !
b1111 %
b100 )
1"
#770
0"
#775
b11111 !
b11111 %
b101 )
1"
#780
0"
#785
b0 !
b0 %
b0 )
1"
#790
0"
#795
b1 !
b1 %
b1 )
1"
#800
0"
#805
b11 !
b11 %
b10 )
1"
#810
0"
#815
b111 !
b111 %
b11 )
1"
#820
0"
#825
b1111 !
b1111 %
b100 )
1"
#830
0"
#835
b11111 !
b11111 %
b101 )
1"
#840
0"
#845
b0 !
b0 %
b0 )
1"
#850
0"
#855
b1 !
b1 %
b1 )
1"
#860
0"
#865
b11 !
b11 %
b10 )
1"
#870
0"
#875
b111 !
b111 %
b11 )
1"
#880
0"
#885
b1111 !
b1111 %
b100 )
1"
#890
0"
#895
b11111 !
b11111 %
b101 )
1"
#900
0"
#905
b0 !
b0 %
b0 )
1"
#910
0"
#915
b1 !
b1 %
b1 )
1"
#920
0"
#925
b11 !
b11 %
b10 )
1"
#930
0"
#935
b111 !
b111 %
b11 )
1"
#940
0"
#945
b1111 !
b1111 %
b100 )
1"
#950
0"
#955
b11111 !
b11111 %
b101 )
1"
#960
0"
#965
b0 !
b0 %
b0 )
1"
#970
0"
#975
b1 !
b1 %
b1 )
1"
#980
0"
#985
b11 !
b11 %
b10 )
1"
#990
0"
#995
b111 !
b111 %
b11 )
1"
