electronica/Laba2/code/pmw_led/src/pwm_led.v
module pwm_led
#(parameter  LED_COUNT = 6, parameter COOLDOWN = 21) // для симуляции COOLDOWN = 3, для запуска 21
(
    input clk,
    input  up,
    input down,
    output [LED_COUNT-1:0] led  
);


reg [2:0] shift;
reg [COOLDOWN-1:0] cooldown;
reg [2:0] counter;

always @(posedge clk)
begin
    if (counter < LED_COUNT-1)
        counter <= counter + 1'b1;
    else
        counter <= 0;
end

always @(posedge clk)
begin
    if (!cooldown)
    begin
        if (!up)
        begin
            cooldown <= 2**COOLDOWN-1;
            if (shift < LED_COUNT-1)
                shift <= shift + 1'b1;
            else
                shift <= 0;
    end
    else if (!down)
    begin
        cooldown <= 2**COOLDOWN-1;
        if (shift > 0)
            shift <= shift - 1'b1;
        else
            shift <= LED_COUNT-1;
        end
    end
    else
        cooldown <= cooldown - 1'b1;
end

genvar i;
generate
        for (i = 0; i < LED_COUNT; i = i + 1)
        begin : led_block  
            assign led[i] = counter > i % LED_COUNT;
        end
endgenerate

endmodule

electronica/Laba2/code/pmw_led/src/pwm_led_tb.v
`timescale 1ns / 1ns

module pwm_led_tb();

reg clk;  // Тактовый сигнал
reg up;
reg down;
wire [5:0] led;  // Светодиоды

// Экземпляр тестируемого модуля
pwm_led #(6, 21) uut(.clk(clk), .up(up), .down(down), .led(led));

// Генерация тактового сигнала с периодом 10 нс (частота 100 МГц)
initial begin
    clk = 0;
    forever #(5) clk = ~clk;  // Период 10 нс
end

initial
begin
    up <= 1;
    down <= 1;
    #20 up <= 0;
    #180 up <= 1;
    #200 down <= 0;
    #200 down <= 1;
end


// Завершение симуляции через 1000 нс
initial begin
    #1000 $finish;
end

// Сохранение результата симуляции в файл VCD для анализа
initial begin
    $dumpfile("pwm_led_out.vcd");
    $dumpvars(0, pwm_led_tb);
end

endmodule

electronica/Laba2/code/pmw_led/pwm_led_out.vcd
$date
	Fri Oct 18 11:57:02 2024
$end
$version
	Icarus Verilog
$end
$timescale
	1ns
$end
$scope module pwm_led_tb $end
$var wire 6 ! led [5:0] $end
$var reg 1 " clk $end
$var reg 1 # down $end
$var reg 1 $ up $end
$scope module uut $end
$var wire 1 " clk $end
$var wire 1 # down $end
$var wire 1 $ up $end
$var wire 6 % led [5:0] $end
$var parameter 32 & COOLDOWN $end
$var parameter 32 ' LED_COUNT $end
$var reg 21 ( cooldown [20:0] $end
$var reg 3 ) counter [2:0] $end
$var reg 3 * shift [2:0] $end
$scope begin led_block[0] $end
$var parameter 2 + i $end
$upscope $end
$scope begin led_block[1] $end
$var parameter 2 , i $end
$upscope $end
$scope begin led_block[2] $end
$var parameter 3 - i $end
$upscope $end
$scope begin led_block[3] $end
$var parameter 3 . i $end
$upscope $end
$scope begin led_block[4] $end
$var parameter 4 / i $end
$upscope $end
$scope begin led_block[5] $end
$var parameter 4 0 i $end
$upscope $end
$upscope $end
$upscope $end
$enddefinitions $end
$comment Show the parameter values. $end
$dumpall
b101 0
b100 /
b11 .
b10 -
b1 ,
b0 +
b110 '
b10101 &
$end
#0
$dumpvars
b0 *
b0 )
b0 (
b0 %
1$
1#
0"
b0 !
$end
#5
b1 !
b1 %
b1 )
1"
#10
0"
#15
b11 !
b11 %
b10 )
1"
#20
0$
0"
#25
b11 )
b100011 !
b100011 %
b1 *
b111111111111111111111 (
1"
#30
0"
#35
b111111111111111111110 (
b100111 !
b100111 %
b100 )
1"
#40
0"
#45
b101111 !
b101111 %
b101 )
b111111111111111111101 (
1"
#50
0"
#55
b111111111111111111100 (
b0 !
b0 %
b0 )
1"
#60
0"
#65
b100000 !
b100000 %
b1 )
b111111111111111111011 (
1"
#70
0"
#75
b111111111111111111010 (
b100001 !
b100001 %
b10 )
1"
#80
0"
#85
b100011 !
b100011 %
b11 )
b111111111111111111001 (
1"
#90
0"
#95
b111111111111111111000 (
b100111 !
b100111 %
b100 )
1"
#100
0"
#105
b101111 !
b101111 %
b101 )
b111111111111111110111 (
1"
#110
0"
#115
b111111111111111110110 (
b0 !
b0 %
b0 )
1"
#120
0"
#125
b100000 !
b100000 %
b1 )
b111111111111111110101 (
1"
#130
0"
#135
b111111111111111110100 (
b100001 !
b100001 %
b10 )
1"
#140
0"
#145
b100011 !
b100011 %
b11 )
b111111111111111110011 (
1"
#150
0"
#155
b111111111111111110010 (
b100111 !
b100111 %
b100 )
1"
#160
0"
#165
b101111 !
b101111 %
b101 )
b111111111111111110001 (
1"
#170
0"
#175
b111111111111111110000 (
b0 !
b0 %
b0 )
1"
#180
0"
#185
b100000 !
b100000 %
b1 )
b111111111111111101111 (
1"
#190
0"
#195
b111111111111111101110 (
b100001 !
b100001 %
b10 )
1"
#200
1$
0"
#205
b100011 !
b100011 %
b11 )
b111111111111111101101 (
1"
#210
0"
#215
b111111111111111101100 (
b100111 !
b100111 %
b100 )
1"
#220
0"
#225
b101111 !
b101111 %
b101 )
b111111111111111101011 (
1"
#230
0"
#235
b111111111111111101010 (
b0 !
b0 %
b0 )
1"
#240
0"
#245
b100000 !
b100000 %
b1 )
b111111111111111101001 (
1"
#250
0"
#255
b111111111111111101000 (
b100001 !
b100001 %
b10 )
1"
#260
0"
#265
b100011 !
b100011 %
b11 )
b111111111111111100111 (
1"
#270
0"
#275
b111111111111111100110 (
b100111 !
b100111 %
b100 )
1"
#280
0"
#285
b101111 !
b101111 %
b101 )
b111111111111111100101 (
1"
#290
0"
#295
b111111111111111100100 (
b0 !
b0 %
b0 )
1"
#300
0"
#305
b100000 !
b100000 %
b1 )
b111111111111111100011 (
1"
#310
0"
#315
b111111111111111100010 (
b100001 !
b100001 %
b10 )
1"
#320
0"
#325
b100011 !
b100011 %
b11 )
b111111111111111100001 (
1"
#330
0"
#335
b111111111111111100000 (
b100111 !
b100111 %
b100 )
1"
#340
0"
#345
b101111 !
b101111 %
b101 )
b111111111111111011111 (
1"
#350
0"
#355
b111111111111111011110 (
b0 !
b0 %
b0 )
1"
#360
0"
#365
b100000 !
b100000 %
b1 )
b111111111111111011101 (
1"
#370
0"
#375
b111111111111111011100 (
b100001 !
b100001 %
b10 )
1"
#380
0"
#385
b100011 !
b100011 %
b11 )
b111111111111111011011 (
1"
#390
0"
#395
b111111111111111011010 (
b100111 !
b100111 %
b100 )
1"
#400
0#
0"
#405
b101111 !
b101111 %
b101 )
b111111111111111011001 (
1"
#410
0"
#415
b111111111111111011000 (
b0 !
b0 %
b0 )
1"
#420
0"
#425
b100000 !
b100000 %
b1 )
b111111111111111010111 (
1"
#430
0"
#435
b111111111111111010110 (
b100001 !
b100001 %
b10 )
1"
#440
0"
#445
b100011 !
b100011 %
b11 )
b111111111111111010101 (
1"
#450
0"
#455
b111111111111111010100 (
b100111 !
b100111 %
b100 )
1"
#460
0"
#465
b101111 !
b101111 %
b101 )
b111111111111111010011 (
1"
#470
0"
#475
b111111111111111010010 (
b0 !
b0 %
b0 )
1"
#480
0"
#485
b100000 !
b100000 %
b1 )
b111111111111111010001 (
1"
#490
0"
#495
b111111111111111010000 (
b100001 !
b100001 %
b10 )
1"
#500
0"
#505
b100011 !
b100011 %
b11 )
b111111111111111001111 (
1"
#510
0"
#515
b111111111111111001110 (
b100111 !
b100111 %
b100 )
1"
#520
0"
#525
b101111 !
b101111 %
b101 )
b111111111111111001101 (
1"
#530
0"
#535
b111111111111111001100 (
b0 !
b0 %
b0 )
1"
#540
0"
#545
b100000 !
b100000 %
b1 )
b111111111111111001011 (
1"
#550
0"
#555
b111111111111111001010 (
b100001 !
b100001 %
b10 )
1"
#560
0"
#565
b100011 !
b100011 %
b11 )
b111111111111111001001 (
1"
#570
0"
#575
b111111111111111001000 (
b100111 !
b100111 %
b100 )
1"
#580
0"
#585
b101111 !
b101111 %
b101 )
b111111111111111000111 (
1"
#590
0"
#595
b111111111111111000110 (
b0 !
b0 %
b0 )
1"
#600
1#
0"
#605
b100000 !
b100000 %
b1 )
b111111111111111000101 (
1"
#610
0"
#615
b111111111111111000100 (
b100001 !
b100001 %
b10 )
1"
#620
0"
#625
b100011 !
b100011 %
b11 )
b111111111111111000011 (
1"
#630
0"
#635
b111111111111111000010 (
b100111 !
b100111 %
b100 )
1"
#640
0"
#645
b101111 !
b101111 %
b101 )
b111111111111111000001 (
1"
#650
0"
#655
b111111111111111000000 (
b0 !
b0 %
b0 )
1"
#660
0"
#665
b100000 !
b100000 %
b1 )
b111111111111110111111 (
1"
#670
0"
#675
b111111111111110111110 (
b100001 !
b100001 %
b10 )
1"
#680
0"
#685
b100011 !
b100011 %
b11 )
b111111111111110111101 (
1"
#690
0"
#695
b111111111111110111100 (
b100111 !
b100111 %
b100 )
1"
#700
0"
#705
b101111 !
b101111 %
b101 )
b111111111111110111011 (
1"
#710
0"
#715
b111111111111110111010 (
b0 !
b0 %
b0 )
1"
#720
0"
#725
b100000 !
b100000 %
b1 )
b111111111111110111001 (
1"
#730
0"
#735
b111111111111110111000 (
b100001 !
b100001 %
b10 )
1"
#740
0"
#745
b100011 !
b100011 %
b11 )
b111111111111110110111 (
1"
#750
0"
#755
b111111111111110110110 (
b100111 !
b100111 %
b100 )
1"
#760
0"
#765
b101111 !
b101111 %
b101 )
b111111111111110110101 (
1"
#770
0"
#775
b111111111111110110100 (
b0 !
b0 %
b0 )
1"
#780
0"
#785
b100000 !
b100000 %
b1 )
b111111111111110110011 (
1"
#790
0"
#795
b111111111111110110010 (
b100001 !
b100001 %
b10 )
1"
#800
0"
#805
b100011 !
b100011 %
b11 )
b111111111111110110001 (
1"
#810
0"
#815
b111111111111110110000 (
b100111 !
b100111 %
b100 )
1"
#820
0"
#825
b101111 !
b101111 %
b101 )
b111111111111110101111 (
1"
#830
0"
#835
b111111111111110101110 (
b0 !
b0 %
b0 )
1"
#840
0"
#845
b100000 !
b100000 %
b1 )
b111111111111110101101 (
1"
#850
0"
#855
b111111111111110101100 (
b100001 !
b100001 %
b10 )
1"
#860
0"
#865
b100011 !
b100011 %
b11 )
b111111111111110101011 (
1"
#870
0"
#875
b111111111111110101010 (
b100111 !
b100111 %
b100 )
1"
#880
0"
#885
b101111 !
b101111 %
b101 )
b111111111111110101001 (
1"
#890
0"
#895
b111111111111110101000 (
b0 !
b0 %
b0 )
1"
#900
0"
#905
b100000 !
b100000 %
b1 )
b111111111111110100111 (
1"
#910
0"
#915
b111111111111110100110 (
b100001 !
b100001 %
b10 )
1"
#920
0"
#925
b100011 !
b100011 %
b11 )
b111111111111110100101 (
1"
#930
0"
#935
b111111111111110100100 (
b100111 !
b100111 %
b100 )
1"
#940
0"
#945
b101111 !
b101111 %
b101 )
b111111111111110100011 (
1"
#950
0"
#955
b111111111111110100010 (
b0 !
b0 %
b0 )
1"
#960
0"
#965
b100000 !
b100000 %
b1 )
b111111111111110100001 (
1"
#970
0"
#975
b111111111111110100000 (
b100001 !
b100001 %
b10 )
1"
#980
0"
#985
b100011 !
b100011 %
b11 )
b111111111111110011111 (
1"
#990
0"
#995
b111111111111110011110 (
b100111 !
b100111 %
b100 )
1"
