electronica/Laba4/code/src/indicator.v
module indicator 
(
    input clk,
    output [3:0] digits,
    output [7:0] segments
);

reg [7:0] DIGITS [0:10];

initial begin
    DIGITS[0] = 'b11000000; // 0: ABCDEF
    DIGITS[1] = 'b11111001; // 1: BC
    DIGITS[2] = 'b10100100; // 2: ABDEG
    DIGITS[3] = 'b10110000; // 3: ABCDG
    DIGITS[4] = 'b10011001; // 4: BCFG
    DIGITS[5] = 'b10010010; // 5: ACDFG
    DIGITS[6] = 'b10000010; // 6: ACDEFG
    DIGITS[7] = 'b11111000; // 7: ABC
    DIGITS[8] = 'b10000000; // 8: ABCDEFG
    DIGITS[9] = 'b10010000;  // 9: ABCDFG
    DIGITS[10] = 8'b0;  // ALL
end

localparam DELAY = 12;

reg [3:0] delay;
reg [1:0] digit_index;
reg [7:0] active_segment;

initial begin
    delay = 0;
    digit_index = 3;
end

always @(posedge clk) begin
    if (!delay) begin
        delay <= DELAY;
        digit_index <= digit_index + 1'b1;
    end
    else delay <= delay - 1'b1;
end

always @(*) begin
    case (digit_index)
        0: active_segment = DIGITS[3];
        1: active_segment = DIGITS[3];
        2: active_segment = DIGITS[6];
        3: active_segment = DIGITS[3];
        default: active_segment = DIGITS[10];
    endcase
end

assign digits = 1'b0001 << digit_index;
assign segments = active_segment;

endmodule

electronica/Laba4/code/src/indicator_tb.v
`timescale 1ns / 1ns

module indicator_tb();

reg clk;
wire [3:0] digits;
wire [7:0] segments;

indicator uut(.clk(clk), .digits(digits), .segments(segments));

// Генерация тактового сигнала с периодом 10 нс (частота 100 МГц)
initial begin
    clk = 0;
    forever #(5) clk = ~clk;
end

// Завершение симуляции через 1000 нс
initial #1000 $finish;

// Сохранение результата симуляции в файл VCD
initial begin
    $dumpfile("indicator_tb_out.vcd");
    $dumpvars(0, indicator_tb);
end

endmodule

electronica/Laba4/code/indicator_tb_out.vcd
$date
	Fri Oct 18 12:46:41 2024
$end
$version
	Icarus Verilog
$end
$timescale
	1ns
$end
$scope module indicator_tb $end
$var wire 8 ! segments [7:0] $end
$var wire 4 " digits [3:0] $end
$var reg 1 # clk $end
$scope module uut $end
$var wire 1 # clk $end
$var wire 8 $ segments [7:0] $end
$var wire 4 % digits [3:0] $end
$var parameter 32 & DELAY $end
$var reg 8 ' active_segment [7:0] $end
$var reg 4 ( delay [3:0] $end
$var reg 2 ) digit_index [1:0] $end
$upscope $end
$upscope $end
$enddefinitions $end
$comment Show the parameter values. $end
$dumpall
b1100 &
$end
#0
$dumpvars
b11 )
b0 (
b10110000 '
b1000 %
b10110000 $
0#
b1000 "
b10110000 !
$end
#5
b1 "
b1 %
b0 )
b1100 (
1#
#10
0#
#15
b1011 (
1#
#20
0#
#25
b1010 (
1#
#30
0#
#35
b1001 (
1#
#40
0#
#45
b1000 (
1#
#50
0#
#55
b111 (
1#
#60
0#
#65
b110 (
1#
#70
0#
#75
b101 (
1#
#80
0#
#85
b100 (
1#
#90
0#
#95
b11 (
1#
#100
0#
#105
b10 (
1#
#110
0#
#115
b1 (
1#
#120
0#
#125
b0 (
1#
#130
0#
#135
b10 "
b10 %
b1 )
b1100 (
1#
#140
0#
#145
b1011 (
1#
#150
0#
#155
b1010 (
1#
#160
0#
#165
b1001 (
1#
#170
0#
#175
b1000 (
1#
#180
0#
#185
b111 (
1#
#190
0#
#195
b110 (
1#
#200
0#
#205
b101 (
1#
#210
0#
#215
b100 (
1#
#220
0#
#225
b11 (
1#
#230
0#
#235
b10 (
1#
#240
0#
#245
b1 (
1#
#250
0#
#255
b0 (
1#
#260
0#
#265
b10000010 !
b10000010 $
b10000010 '
b100 "
b100 %
b10 )
b1100 (
1#
#270
0#
#275
b1011 (
1#
#280
0#
#285
b1010 (
1#
#290
0#
#295
b1001 (
1#
#300
0#
#305
b1000 (
1#
#310
0#
#315
b111 (
1#
#320
0#
#325
b110 (
1#
#330
0#
#335
b101 (
1#
#340
0#
#345
b100 (
1#
#350
0#
#355
b11 (
1#
#360
0#
#365
b10 (
1#
#370
0#
#375
b1 (
1#
#380
0#
#385
b0 (
1#
#390
0#
#395
b10110000 !
b10110000 $
b10110000 '
b1000 "
b1000 %
b11 )
b1100 (
1#
#400
0#
#405
b1011 (
1#
#410
0#
#415
b1010 (
1#
#420
0#
#425
b1001 (
1#
#430
0#
#435
b1000 (
1#
#440
0#
#445
b111 (
1#
#450
0#
#455
b110 (
1#
#460
0#
#465
b101 (
1#
#470
0#
#475
b100 (
1#
#480
0#
#485
b11 (
1#
#490
0#
#495
b10 (
1#
#500
0#
#505
b1 (
1#
#510
0#
#515
b0 (
1#
#520
0#
#525
b1 "
b1 %
b0 )
b1100 (
1#
#530
0#
#535
b1011 (
1#
#540
0#
#545
b1010 (
1#
#550
0#
#555
b1001 (
1#
#560
0#
#565
b1000 (
1#
#570
0#
#575
b111 (
1#
#580
0#
#585
b110 (
1#
#590
0#
#595
b101 (
1#
#600
0#
#605
b100 (
1#
#610
0#
#615
b11 (
1#
#620
0#
#625
b10 (
1#
#630
0#
#635
b1 (
1#
#640
0#
#645
b0 (
1#
#650
0#
#655
b10 "
b10 %
b1 )
b1100 (
1#
#660
0#
#665
b1011 (
1#
#670
0#
#675
b1010 (
1#
#680
0#
#685
b1001 (
1#
#690
0#
#695
b1000 (
1#
#700
0#
#705
b111 (
1#
#710
0#
#715
b110 (
1#
#720
0#
#725
b101 (
1#
#730
0#
#735
b100 (
1#
#740
0#
#745
b11 (
1#
#750
0#
#755
b10 (
1#
#760
0#
#765
b1 (
1#
#770
0#
#775
b0 (
1#
#780
0#
#785
b10000010 !
b10000010 $
b10000010 '
b100 "
b100 %
b10 )
b1100 (
1#
#790
0#
#795
b1011 (
1#
#800
0#
#805
b1010 (
1#
#810
0#
#815
b1001 (
1#
#820
0#
#825
b1000 (
1#
#830
0#
#835
b111 (
1#
#840
0#
#845
b110 (
1#
#850
0#
#855
b101 (
1#
#860
0#
#865
b100 (
1#
#870
0#
#875
b11 (
1#
#880
0#
#885
b10 (
1#
#890
0#
#895
b1 (
1#
#900
0#
#905
b0 (
1#
#910
0#
#915
b10110000 !
b10110000 $
b10110000 '
b1000 "
b1000 %
b11 )
b1100 (
1#
#920
0#
#925
b1011 (
1#
#930
0#
#935
b1010 (
1#
#940
0#
#945
b1001 (
1#
#950
0#
#955
b1000 (
1#
#960
0#
#965
b111 (
1#
#970
0#
#975
b110 (
1#
#980
0#
#985
b101 (
1#
#990
0#
#995
b100 (
1#
